LICENSE
naif_eop_predict/__init__.py
naif_eop_predict/earth_200101_990827_predict.bpc
naif_eop_predict/earth_200101_990827_predict.md5
naif_eop_predict/fetch.py
naif_eop_predict/tests/__init__.py
naif_eop_predict/tests/test_naif_eop_predict.py
naif_eop_predict-2024.8.28.1.dist-info/licenses/LICENSE
naif_eop_predict-2024.8.28.1.dist-info/METADATA
naif_eop_predict-2024.8.28.1.dist-info/WHEEL
naif_eop_predict-2024.8.28.1.dist-info/top_level.txt
naif_eop_predict-2024.8.28.1.dist-info/RECORD
